CHANGES.txt
LICENSE.txt
MANIFEST.in
README.txt
bootstrap.py
buildout.cfg
setup.py
.eggs/README.txt
.eggs/bleach-3.3.1-py2.7.egg/EGG-INFO/requires.txt
.eggs/bleach-3.3.1-py2.7.egg/EGG-INFO/top_level.txt
.eggs/bleach-3.3.1-py2.7.egg/bleach/_vendor/vendor.txt
.eggs/bleach-3.3.1-py2.7.egg/bleach/_vendor/html5lib-1.1.dist-info/top_level.txt
eggs/BTrees-6.1-py3.10-win-amd64.egg/EGG-INFO/LICENSE.txt
eggs/BTrees-6.1-py3.10-win-amd64.egg/EGG-INFO/requires.txt
eggs/BTrees-6.1-py3.10-win-amd64.egg/EGG-INFO/top_level.txt
eggs/cffi-1.17.1-py3.10-win-amd64.egg/EGG-INFO/entry_points.txt
eggs/cffi-1.17.1-py3.10-win-amd64.egg/EGG-INFO/requires.txt
eggs/cffi-1.17.1-py3.10-win-amd64.egg/EGG-INFO/top_level.txt
eggs/cffi-2.0.0-py3.10-win-amd64.egg/EGG-INFO/entry_points.txt
eggs/cffi-2.0.0-py3.10-win-amd64.egg/EGG-INFO/requires.txt
eggs/cffi-2.0.0-py3.10-win-amd64.egg/EGG-INFO/top_level.txt
eggs/coverage-7.10.3-py3.10.egg/EGG-INFO/entry_points.txt
eggs/coverage-7.10.3-py3.10.egg/EGG-INFO/requires.txt
eggs/coverage-7.10.3-py3.10.egg/EGG-INFO/top_level.txt
eggs/coverage-7.10.3-py3.10.egg/EGG-INFO/licenses/LICENSE.txt
eggs/coverage-7.10.4-py3.10.egg/EGG-INFO/entry_points.txt
eggs/coverage-7.10.4-py3.10.egg/EGG-INFO/requires.txt
eggs/coverage-7.10.4-py3.10.egg/EGG-INFO/top_level.txt
eggs/coverage-7.10.4-py3.10.egg/EGG-INFO/licenses/LICENSE.txt
eggs/coverage-7.10.7-py3.10-win-amd64.egg/EGG-INFO/entry_points.txt
eggs/coverage-7.10.7-py3.10-win-amd64.egg/EGG-INFO/requires.txt
eggs/coverage-7.10.7-py3.10-win-amd64.egg/EGG-INFO/top_level.txt
eggs/coverage-7.10.7-py3.10-win-amd64.egg/EGG-INFO/licenses/LICENSE.txt
eggs/future-1.0.0-py3.10.egg/EGG-INFO/LICENSE.txt
eggs/future-1.0.0-py3.10.egg/EGG-INFO/entry_points.txt
eggs/future-1.0.0-py3.10.egg/EGG-INFO/top_level.txt
eggs/lovely.recipe-1.0.0-py3.10.egg/EGG-INFO/SOURCES.txt
eggs/lovely.recipe-1.0.0-py3.10.egg/EGG-INFO/dependency_links.txt
eggs/lovely.recipe-1.0.0-py3.10.egg/EGG-INFO/entry_points.txt
eggs/lovely.recipe-1.0.0-py3.10.egg/EGG-INFO/namespace_packages.txt
eggs/lovely.recipe-1.0.0-py3.10.egg/EGG-INFO/requires.txt
eggs/lovely.recipe-1.0.0-py3.10.egg/EGG-INFO/top_level.txt
eggs/lovely.recipe-1.0.0-py3.10.egg/lovely/recipe/egg/README.txt
eggs/lovely.recipe-1.0.0-py3.10.egg/lovely/recipe/fs/README.txt
eggs/lovely.recipe-1.0.0-py3.10.egg/lovely/recipe/fs/mkdir-root.txt
eggs/lovely.recipe-1.0.0-py3.10.egg/lovely/recipe/i18n/README.txt
eggs/lovely.recipe-1.0.0-py3.10.egg/lovely/recipe/importchecker/README.txt
eggs/multipart-1.3.0-py3.10.egg/EGG-INFO/requires.txt
eggs/persistent-6.1.1-py3.10-win-amd64.egg/EGG-INFO/LICENSE.txt
eggs/persistent-6.1.1-py3.10-win-amd64.egg/EGG-INFO/requires.txt
eggs/persistent-6.1.1-py3.10-win-amd64.egg/EGG-INFO/top_level.txt
eggs/persistent-6.2-py3.10-win-amd64.egg/EGG-INFO/LICENSE.txt
eggs/persistent-6.2-py3.10-win-amd64.egg/EGG-INFO/requires.txt
eggs/persistent-6.2-py3.10-win-amd64.egg/EGG-INFO/top_level.txt
eggs/pycparser-2.22-py3.10.egg/EGG-INFO/top_level.txt
eggs/pycparser-2.23-py3.10.egg/EGG-INFO/top_level.txt
eggs/python_gettext-5.0-py3.10.egg/EGG-INFO/top_level.txt
eggs/pytz-2025.2-py3.10.egg/EGG-INFO/LICENSE.txt
eggs/pytz-2025.2-py3.10.egg/EGG-INFO/top_level.txt
eggs/six-1.17.0-py3.10.egg/EGG-INFO/top_level.txt
eggs/transaction-5.0-py3.10.egg/EGG-INFO/LICENSE.txt
eggs/transaction-5.0-py3.10.egg/EGG-INFO/requires.txt
eggs/transaction-5.0-py3.10.egg/EGG-INFO/top_level.txt
eggs/z3c.coverage-2.1.0-py3.10.egg/EGG-INFO/SOURCES.txt
eggs/z3c.coverage-2.1.0-py3.10.egg/EGG-INFO/dependency_links.txt
eggs/z3c.coverage-2.1.0-py3.10.egg/EGG-INFO/entry_points.txt
eggs/z3c.coverage-2.1.0-py3.10.egg/EGG-INFO/namespace_packages.txt
eggs/z3c.coverage-2.1.0-py3.10.egg/EGG-INFO/requires.txt
eggs/z3c.coverage-2.1.0-py3.10.egg/EGG-INFO/top_level.txt
eggs/z3c.coverage-2.1.0-py3.10.egg/z3c/coverage/README.txt
eggs/z3c.coverage-2.1.0-py3.10.egg/z3c/coverage/coveragediff.txt
eggs/z3c.coverage-2.1.0-py3.10.egg/z3c/coverage/sampleinput/decoy.txt
eggs/z3c.testing-2.0-py3.10.egg/EGG-INFO/namespace_packages.txt
eggs/z3c.testing-2.0-py3.10.egg/EGG-INFO/requires.txt
eggs/z3c.testing-2.0-py3.10.egg/EGG-INFO/top_level.txt
eggs/z3c.testing-2.0-py3.10.egg/z3c/testing/BROWSER.txt
eggs/zc.recipe.egg-2.0.7-py3.10.egg/EGG-INFO/SOURCES.txt
eggs/zc.recipe.egg-2.0.7-py3.10.egg/EGG-INFO/dependency_links.txt
eggs/zc.recipe.egg-2.0.7-py3.10.egg/EGG-INFO/entry_points.txt
eggs/zc.recipe.egg-2.0.7-py3.10.egg/EGG-INFO/namespace_packages.txt
eggs/zc.recipe.egg-2.0.7-py3.10.egg/EGG-INFO/requires.txt
eggs/zc.recipe.egg-2.0.7-py3.10.egg/EGG-INFO/top_level.txt
eggs/zc.recipe.testrunner-3.2-py3.10.egg/EGG-INFO/LICENSE.txt
eggs/zc.recipe.testrunner-3.2-py3.10.egg/EGG-INFO/entry_points.txt
eggs/zc.recipe.testrunner-3.2-py3.10.egg/EGG-INFO/namespace_packages.txt
eggs/zc.recipe.testrunner-3.2-py3.10.egg/EGG-INFO/requires.txt
eggs/zc.recipe.testrunner-3.2-py3.10.egg/EGG-INFO/top_level.txt
eggs/zope.annotation-5.1-py3.10.egg/EGG-INFO/LICENSE.txt
eggs/zope.annotation-5.1-py3.10.egg/EGG-INFO/namespace_packages.txt
eggs/zope.annotation-5.1-py3.10.egg/EGG-INFO/requires.txt
eggs/zope.annotation-5.1-py3.10.egg/EGG-INFO/top_level.txt
eggs/zope.browser-3.1-py3.10.egg/EGG-INFO/LICENSE.txt
eggs/zope.browser-3.1-py3.10.egg/EGG-INFO/namespace_packages.txt
eggs/zope.browser-3.1-py3.10.egg/EGG-INFO/requires.txt
eggs/zope.browser-3.1-py3.10.egg/EGG-INFO/top_level.txt
eggs/zope.cachedescriptors-5.1-py3.10.egg/EGG-INFO/LICENSE.txt
eggs/zope.cachedescriptors-5.1-py3.10.egg/EGG-INFO/namespace_packages.txt
eggs/zope.cachedescriptors-5.1-py3.10.egg/EGG-INFO/requires.txt
eggs/zope.cachedescriptors-5.1-py3.10.egg/EGG-INFO/top_level.txt
eggs/zope.component-6.0-py3.10.egg/EGG-INFO/LICENSE.txt
eggs/zope.component-6.0-py3.10.egg/EGG-INFO/namespace_packages.txt
eggs/zope.component-6.0-py3.10.egg/EGG-INFO/requires.txt
eggs/zope.component-6.0-py3.10.egg/EGG-INFO/top_level.txt
eggs/zope.configuration-6.0-py3.10.egg/EGG-INFO/LICENSE.txt
eggs/zope.configuration-6.0-py3.10.egg/EGG-INFO/namespace_packages.txt
