Metadata-Version: 2.1
Name: p01.cgi
Version: 0.6.3
Summary: Replacement for cgi FieldStorage parser
Home-page: http://pypi.python.org/pypi/p01.cgi
Author: Adam Groszer, Roger Ineichen, Projekt01 GmbH
Author-email: dev@projekt01.ch
License: ZPL 2.1
Keywords: Zope3 z3c p01 form parser cgi field storage FieldStorage
Platform: UNKNOWN
Classifier: Development Status :: 4 - Beta
Classifier: Environment :: Web Environment
Classifier: Intended Audience :: Developers
Classifier: License :: OSI Approved :: Zope Public License
Classifier: Programming Language :: Python
Classifier: Natural Language :: English
Classifier: Operating System :: OS Independent
Classifier: Topic :: Internet :: WWW/HTTP
Classifier: Framework :: Zope3
Provides-Extra: test
